Metadata-Version: 1.0
Name: polyprox
Version: 0.4
Summary: Polygonal curve approximation tools
Home-page: https://github.com/geissdoerfer/polyprox
Author: Kai Geissdoerfer
Author-email: kai.geissdoerfer@mailbox.tu-berlin.de
License: UNKNOWN
Platform: UNKNOWN
